{
  "artifact": "instrumentation_alerts",
  "alert_count": 2,
  "alerts": [
    {
      "experiment_id": "EXP-CHECKOUT-FRICTION-001",
      "platform": "ios",
      "segment": "platform=ios",
      "window_start": "2026-04-01T09:25:00+00:00",
      "baseline_event_count": 172.8,
      "observed_event_count": 0,
      "drop_pct": 1.0,
      "alert_level": "critical",
      "suspected_cause": "ios_event_flow_gap"
    },
    {
      "experiment_id": "EXP-CHECKOUT-FRICTION-001",
      "platform": "ios",
      "segment": "platform=ios",
      "window_start": "2026-04-01T09:30:00+00:00",
      "baseline_event_count": 172.8,
      "observed_event_count": 0,
      "drop_pct": 1.0,
      "alert_level": "critical",
      "suspected_cause": "ios_event_flow_gap"
    }
  ]
}